{
    "name_fa": "ماژیک علامت‌گذار پاستلی H512 پنتر",
    "product_type": "فیزیکی",
    "main_category": "لوازم هنری و صنایع دستی > ماژیک علامت‌گذار",
    "brand": "پنتر (Panter)",
    "tags": [
        "هایلایتر پنتر",
        "علامت گذار پاستلی",
        "ماژیک پاستلی پنتر"
    ],
    "unit": "عدد",
    "sku": "1505400512000",
    "weight": "20",
    "stock_status": "موجود",
    "seo_title": "ماژیک علامت‌گذار پاستلی H512 پنتر CH512 تک‌عددی",
    "slug": "panter-pastel-highlighter-h512-pd36",
    "keywords": "هایلایتر پاستلی پنتر، ماژیک علامت گذار پنتر، هایلایتر پنتر H512، خرید هایلایتر پاستلی",
    "short_desc": "ماژیک علامت‌گذار پاستلی پنتر مدل CH-512 تک‌عددی بدنه تخت با جوهر پایه آب غیرسمی و رنگ‌های ملایم، نکات مهم متون را بدون خستگی چشم برجسته می‌سازد.",
    "shopfa_type": "ماژیک و علامت‌گذار دانش‌آموزی (Highlighters)",
    "attributes": [
        {
            "name": "نوع نوک",
            "val": "نمدی تخت (Chisel Nib)"
        },
        {
            "name": "ضخامت خط",
            "val": "۱ تا ۵ میلی‌متر"
        },
        {
            "name": "نوع بسته‌بندی",
            "val": "تک‌عددی"
        },
        {
            "name": "پایه ترکیبات شیمیایی",
            "val": "جوهر پایه آب غیرسمی"
        }
    ],
    "variants": [
        {
            "type": "رنگ جوهر و بدنه",
            "val": "زرد",
            "sku": "1505400512501",
            "stock": "تعیین توسط کاربر",
            "price": "تعیین توسط کاربر"
        },
        {
            "type": "رنگ جوهر و بدنه",
            "val": "سبز",
            "sku": "1505400512502",
            "stock": "تعیین توسط کاربر",
            "price": "تعیین توسط کاربر"
        },
        {
            "type": "رنگ جوهر و بدنه",
            "val": "نارنجی",
            "sku": "1505400512503",
            "stock": "تعیین توسط کاربر",
            "price": "تعیین توسط کاربر"
        },
        {
            "type": "رنگ جوهر و بدنه",
            "val": "آبی",
            "sku": "1505400512504",
            "stock": "تعیین توسط کاربر",
            "price": "تعیین توسط کاربر"
        },
        {
            "type": "رنگ جوهر و بدنه",
            "val": "بنفش",
            "sku": "1505400512505",
            "stock": "تعیین توسط کاربر",
            "price": "تعیین توسط کاربر"
        },
        {
            "type": "رنگ جوهر و بدنه",
            "val": "صورتی",
            "sku": "1505400512506",
            "stock": "تعیین توسط کاربر",
            "price": "تعیین توسط کاربر"
        }
    ],
    "long_html": "<div style=\"direction: rtl; font-family: Vazirmatn, Tahoma, Arial, sans-serif; padding: 25px; border: 1px solid #e9d5ff; border-radius: 16px; background-color: #ffffff !important; max-width: 800px; margin: auto; line-height: 1.8; color: #0f172a !important; box-shadow: 0 4px 15px rgba(0,0,0,0.05);\">\n  <h2 style=\"color: #4c1d95 !important; border-bottom: 2px solid #8b5cf6; padding-bottom: 12px; font-size: 20px; font-weight: bold; margin-bottom: 18px; text-align: center;\">ماژیک علامت‌گذار پاستلی H512 پنتر؛ ارگونومی بصری و محافظت از سلامت بینایی</h2>\n  \n  <p style=\"color: #0f172a !important; font-size: 15px; margin-bottom: 15px;\">رنگ‌های فلورسنت شدید و درخشان سنتی پس از چند دقیقه مطالعه، شبکیه چشم را خسته کرده و تمرکز را مختل می‌سازند. ماژیک هایلایتر پاستلی پنتر مدل CH-512 با بهره‌گیری از طیف رنگ‌های ملایم، کنتراست بی‌نظیری را بر روی متون چاپی بدون آسیب بصری و خستگی چشم به وجود می‌آورد.</p>\n\n  <h3 style=\"color: #6d28d9 !important; font-size: 16px; font-weight: bold; margin-top: 22px; margin-bottom: 12px;\">ویژگی‌های ماژیک علامت‌گذار پاستلی پنتر:</h3>\n  <ul style=\"margin-right: 20px; margin-bottom: 20px; color: #0f172a !important;\">\n    <li style=\"margin-bottom: 8px; color: #0f172a !important;\"><strong style=\"color: #000000 !important;\">رنگ‌های ملایم پاستلی:</strong> شامل ۶ رنگ زرد، سبز، نارنجی، آبی، بنفش و صورتی که بدنه پلاستیکی محصول نیز کاملاً هماهنگ با رنگ جوهر آن است.</li>\n    <li style=\"margin-bottom: 8px; color: #0f172a !important;\"><strong style=\"color: #000000 !important;\">نوک نمدی تخت فیبر فشرده:</strong> طراحی نوک باکیفیت جهت ترسیم خطوطی با ضخامت‌های گوناگون از ۱ تا ۵ میلی‌متر برای کاربری‌های مختلف متنی.</li>\n    <li style=\"margin-bottom: 8px; color: #0f172a !important;\"><strong style=\"color: #000000 !important;\">جوهر پایه آب غیرسمی:</strong> فرمولاسیون فاقد مواد شیمیایی حساسیت‌زا و بودار، فاقد نفوذ به لایه‌های پشتی کاغذهای استاندارد تحریر.</li>\n    <li style=\"margin-bottom: 8px; color: #0f172a !important;\"><strong style=\"color: #000000 !important;\">طراحی تخت بدنه:</strong> مقطع هندسی تخت بدنه مانع از غلتیدن ناگهانی قلم روی سطوح شیب‌دار زنگ‌های تحصیلی می‌گردد.</li>\n  </ul>\n\n  <div style=\"margin-top: 25px; padding: 18px; border-right: 4px solid #a855f7; background-color: #faf5ff !important; border-radius: 10px; border: 1px solid #f3e8ff;\">\n    <h4 style=\"color: #6d28d9 !important; font-weight: bold; font-size: 15px; margin-bottom: 10px;\">اطلاعات بسته‌بندی تک‌عددی:</h4>\n    <p style=\"color: #0f172a !important; margin-bottom: 6px; font-weight: bold;\">۱. وزن ناخالص و ابعاد هر ماژیک چقدر است؟</p>\n    <p style=\"color: #1e293b !important; margin-right: 10px; margin-bottom: 12px;\">بر اساس الگوی تک‌عددی، وزن ناخالص فیزیکی هر هایلایتر ۲۰ گرم و ابعاد آن ۱۲ × ۲.۵ × ۲ سانتی‌متر است.</p>\n    <p style=\"color: #0f172a !important; margin-bottom: 6px; font-weight: bold;\">۲. آیا بدنه محصول باکیفیت است؟</p>\n    <p style=\"color: #1e293b !important; margin-right: 10px; margin-bottom: 12px;\">بله، بدنه پلاستیکی از مواد نو غیربازیافتی بسیار مقاوم با درپوش باکیفیت سرمه‌ای رنگ طراحی شده که از تبخیر و خشک شدن زودرس جوهر ممانعت می‌کند.</p>\n  </div>\n</div>"
}